[
    {
        "policyId": "22261a20-b7c1-4f86-9209-f7357746f661",
        "identification": "string",
        "documentationDeliveryDate": "2022-12-31",
        "status": "ABERTO",
        "statusAlterationDate": "2022-12-31",
        "occurrenceDate": "2022-12-31",
        "warningDate": "2022-12-31",
        "thirdPartyClaimDate": "2022-12-31",
        "amount": {
            "amount": "2000.00",
            "unit": {
                "code": "R$",
                "description": "BRL"
            }
        },
        "denialJustification": "RISCO_EXCLUIDO",
        "denialJustificationDescription": "string",
        "coverages": [
            {
                "insuredObjectId": "string",
                "branch": "0111",
                "code": "GRANIZO",
                "description": "string",
                "warningDate": "2022-12-31",
                "thirdPartyClaimDate": "2022-12-31"
            }
        ],
        "branchInfo": {
            "surveyDate": "2022-12-31",
            "surveyAddress": "string",
            "surveyCountrySubDivision": "SP",
            "surveyPostCode": "10000000",
            "surveyCountryCode": "BRA"
        }
    }
]